{
  "image_id": "Cluster_171_frame_frame_021399_00",
  "original": "original.jpg",
  "visualization": "visualization.jpg",
  "num_items": 2,
  "items": [
    {
      "index": 0,
      "name": "lemon wedge",
      "description": "yellow lemon wedge with a textured surface",
      "bbox": [
        822,
        808,
        1005,
        1068
      ],
      "crop": "crops/item_000.jpg",
      "mask": "masks/item_000_mask.png",
      "sam_score": 0.9846
    },
    {
      "index": 1,
      "name": "kabsa rice",
      "description": "golden-yellow rice grains mixed with orange carrot slivers and brown lentils",
      "bbox": [
        29,
        124,
        1146,
        1048
      ],
      "crop": "crops/item_001.jpg",
      "mask": "masks/item_001_mask.png",
      "sam_score": 0.9679
    }
  ],
  "stage1_time": 2.13,
  "stage2_time": 0.35,
  "match_results": null
}